odoo/addons/sale_order_invoicing_grouping_criteria/README.rst
odoo/addons/sale_order_invoicing_grouping_criteria/__init__.py
odoo/addons/sale_order_invoicing_grouping_criteria/__manifest__.py
odoo/addons/sale_order_invoicing_grouping_criteria/i18n/ca.po
odoo/addons/sale_order_invoicing_grouping_criteria/i18n/de.po
odoo/addons/sale_order_invoicing_grouping_criteria/i18n/es.po
odoo/addons/sale_order_invoicing_grouping_criteria/i18n/fr.po
odoo/addons/sale_order_invoicing_grouping_criteria/i18n/it.po
odoo/addons/sale_order_invoicing_grouping_criteria/i18n/sale_order_invoicing_grouping_criteria.pot
odoo/addons/sale_order_invoicing_grouping_criteria/models/__init__.py
odoo/addons/sale_order_invoicing_grouping_criteria/models/res_company.py
odoo/addons/sale_order_invoicing_grouping_criteria/models/res_config_settings.py
odoo/addons/sale_order_invoicing_grouping_criteria/models/res_partner.py
odoo/addons/sale_order_invoicing_grouping_criteria/models/sale_invoicing_grouping_criteria.py
odoo/addons/sale_order_invoicing_grouping_criteria/models/sale_order.py
odoo/addons/sale_order_invoicing_grouping_criteria/readme/CONFIGURE.md
odoo/addons/sale_order_invoicing_grouping_criteria/readme/CONTRIBUTORS.md
odoo/addons/sale_order_invoicing_grouping_criteria/readme/DESCRIPTION.md
odoo/addons/sale_order_invoicing_grouping_criteria/readme/USAGE.md
odoo/addons/sale_order_invoicing_grouping_criteria/security/ir.model.access.csv
odoo/addons/sale_order_invoicing_grouping_criteria/static/description/icon.png
odoo/addons/sale_order_invoicing_grouping_criteria/static/description/index.html
odoo/addons/sale_order_invoicing_grouping_criteria/tests/__init__.py
odoo/addons/sale_order_invoicing_grouping_criteria/tests/test_sale_order_invoicing_group_criteria.py
odoo/addons/sale_order_invoicing_grouping_criteria/views/res_config_settings_views.xml
odoo/addons/sale_order_invoicing_grouping_criteria/views/res_partner_views.xml
odoo_addon_sale_order_invoicing_grouping_criteria-18.0.1.0.0.4.dist-info/METADATA
odoo_addon_sale_order_invoicing_grouping_criteria-18.0.1.0.0.4.dist-info/WHEEL
odoo_addon_sale_order_invoicing_grouping_criteria-18.0.1.0.0.4.dist-info/top_level.txt
odoo_addon_sale_order_invoicing_grouping_criteria-18.0.1.0.0.4.dist-info/RECORD
